{
    "title" : "RPMManual",
    "description" : "RPM MANUAL",
    "author" : "Zhou Wei",
    "generator": "site",
    "language" : "zh-hans",
    "gitbook" : "3.2.2",
    "links" : {
        "sidebar" : {
            "说明书主页" : "https://weizhou.gitbooks.io/gitbook/"
        }
    },
   "plugins": [
     "anchor-navigation-ex",
     "search-jieba",
    "-lunr",
	  "-highlight",
	  "prism",
    "emphasize",
  	"splitter"
    ],
    "pluginsConfig": {
        "github": {
            "url": "https://github.com/DrWeiZhou"
        },
        "sharing": {
            "weibo": true,
            "facebook": true,
            "twitter": true,
            "google": false,
            "instapaper": false,
             "vk": false,
            "all": [
                "facebook", "google", "twitter",
                "weibo", "instapaper"
            ]
        },
      "anchor-navigation-ex":{
        "associatedWithSummary": true,
          "mode": "" 
      },
      "theme-default": {
           "showLevel": true
      }
    }
}
